prob_spaces/__init__.py
prob_spaces/box.py
prob_spaces/converter.py
prob_spaces/dict.py
prob_spaces/discrete.py
prob_spaces/multi_discrete.py
prob_spaces/tuple.py
prob_spaces/dists/__init__.py
prob_spaces/dists/categorical.py
prob_spaces-0.1.0.dist-info/METADATA
prob_spaces-0.1.0.dist-info/WHEEL
prob_spaces-0.1.0.dist-info/licenses/LICENSE
prob_spaces-0.1.0.dist-info/RECORD
