Metadata-Version: 2.4
Name: prob-spaces
Version: 0.1.0
Author-email: DanielAvdar <66269169+DanielAvdar@users.noreply.github.com>
License: MIT
License-File: LICENSE
Keywords: python
Classifier: Intended Audience :: Developers
Classifier: Intended Audience :: Education
Classifier: License :: OSI Approved :: MIT License
Classifier: Operating System :: OS Independent
Classifier: Programming Language :: Python :: 3
Classifier: Programming Language :: Python :: 3.10
Classifier: Programming Language :: Python :: 3.11
Classifier: Programming Language :: Python :: 3.12
Classifier: Programming Language :: Python :: 3.13
Classifier: Topic :: Scientific/Engineering :: Artificial Intelligence
Requires-Python: >=3.10
Requires-Dist: gymnasium
Requires-Dist: numpy
Requires-Dist: torch
Requires-Dist: torchrl
